[
	{
		"tm": "2022-01-29 00:00",
		"rnum": "1",
		"stnId": "108",
		"stnNm": "서울",
		"ta": "-4.7",
		"taQcflg": "",
		"rn": "",
		"rnQcflg": "",
		"ws": "2.9",
		"wsQcflg": "",
		"wd": "270",
		"wdQcflg": "",
		"hm": "55",
		"hmQcflg": "",
		"pv": "2.4",
		"td": "-12.3",
		"pa": "1013.6",
		"paQcflg": "",
		"ps": "1024.7",
		"psQcflg": "",
		"ss": "",
		"ssQcflg": "9",
		"icsr": "",
		"dsnw": "",
		"hr3Fhsc": "",
		"dc10Tca": "2",
		"dc10LmcsCa": "0",
		"clfmAbbrCd": "Ci",
		"lcsCh": "",
		"vs": "2000",
		"gndSttCd": "",
		"dmstMtphNo": "",
		"ts": "-3.9",
		"tsQcflg": "",
		"m005Te": "-0.1",
		"m01Te": "-0.5",
		"m02Te": "-0.4",
		"m03Te": "0.1"
	},
	{
		"tm": "2022-01-29 01:00",
		"rnum": "2",
		"stnId": "108",
		"stnNm": "서울",
		"ta": "-5.1",
		"taQcflg": "",
		"rn": "",
		"rnQcflg": "",
		"ws": "1.4",
		"wsQcflg": "",
		"wd": "290",
		"wdQcflg": "",
		"hm": "56",
		"hmQcflg": "",
		"pv": "2.3",
		"td": "-12.5",
		"pa": "1013.4",
		"paQcflg": "",
		"ps": "1024.5",
		"psQcflg": "",
		"ss": "",
		"ssQcflg": "9",
		"icsr": "",
		"dsnw": "",
		"hr3Fhsc": "",
		"dc10Tca": "0",
		"dc10LmcsCa": "0",
		"clfmAbbrCd": "",
		"lcsCh": "",
		"vs": "2000",
		"gndSttCd": "",
		"dmstMtphNo": "",
		"ts": "-4.4",
		"tsQcflg": "",
		"m005Te": "-0.1",
		"m01Te": "-0.5",
		"m02Te": "-0.4",
		"m03Te": "0.1"
	},
	{
		"tm": "2022-01-29 02:00",
		"rnum": "3",
		"stnId": "108",
		"stnNm": "서울",
		"ta": "-5.7",
		"taQcflg": "",
		"rn": "",
		"rnQcflg": "",
		"ws": "2.7",
		"wsQcflg": "",
		"wd": "290",
		"wdQcflg": "",
		"hm": "58",
		"hmQcflg": "",
		"pv": "2.3",
		"td": "-12.6",
		"pa": "1013.3",
		"paQcflg": "",
		"ps": "1024.4",
		"psQcflg": "",
		"ss": "",
		"ssQcflg": "9",
		"icsr": "",
		"dsnw": "",
		"hr3Fhsc": "",
		"dc10Tca": "0",
		"dc10LmcsCa": "0",
		"clfmAbbrCd": "",
		"lcsCh": "",
		"vs": "2000",
		"gndSttCd": "",
		"dmstMtphNo": "",
		"ts": "-4.9",
		"tsQcflg": "",
		"m005Te": "-0.2",
		"m01Te": "-0.6",
		"m02Te": "-0.4",
		"m03Te": "0.1"
	},
	{
		"tm": "2022-01-29 03:00",
		"rnum": "4",
		"stnId": "108",
		"stnNm": "서울",
		"ta": "-6.0",
		"taQcflg": "",
		"rn": "",
		"rnQcflg": "",
		"ws": "2.4",
		"wsQcflg": "",
		"wd": "290",
		"wdQcflg": "",
		"hm": "61",
		"hmQcflg": "",
		"pv": "2.4",
		"td": "-12.3",
		"pa": "1013.0",
		"paQcflg": "",
		"ps": "1024.1",
		"psQcflg": "",
		"ss": "",
		"ssQcflg": "9",
		"icsr": "",
		"dsnw": "",
		"hr3Fhsc": "",
		"dc10Tca": "3",
		"dc10LmcsCa": "0",
		"clfmAbbrCd": "Ci",
		"lcsCh": "",
		"vs": "2000",
		"gndSttCd": "",
		"dmstMtphNo": "",
		"ts": "-5.4",
		"tsQcflg": "",
		"m005Te": "-0.3",
		"m01Te": "-0.6",
		"m02Te": "-0.4",
		"m03Te": "0.1"
	},
	{
		"tm": "2022-01-29 04:00",
		"rnum": "5",
		"stnId": "108",
		"stnNm": "서울",
		"ta": "-6.6",
		"taQcflg": "",
		"rn": "",
		"rnQcflg": "",
		"ws": "1.6",
		"wsQcflg": "",
		"wd": "270",
		"wdQcflg": "",
		"hm": "61",
		"hmQcflg": "",
		"pv": "2.3",
		"td": "-12.8",
		"pa": "1012.4",
		"paQcflg": "",
		"ps": "1023.5",
		"psQcflg": "",
		"ss": "",
		"ssQcflg": "9",
		"icsr": "",
		"dsnw": "",
		"hr3Fhsc": "",
		"dc10Tca": "0",
		"dc10LmcsCa": "0",
		"clfmAbbrCd": "",
		"lcsCh": "",
		"vs": "2000",
		"gndSttCd": "",
		"dmstMtphNo": "",
		"ts": "-6.0",
		"tsQcflg": "",
		"m005Te": "-0.4",
		"m01Te": "-0.7",
		"m02Te": "-0.4",
		"m03Te": "0.1"
	},
	{
		"tm": "2022-01-29 05:00",
		"rnum": "6",
		"stnId": "108",
		"stnNm": "서울",
		"ta": "-6.8",
		"taQcflg": "",
		"rn": "",
		"rnQcflg": "",
		"ws": "1.9",
		"wsQcflg": "",
		"wd": "270",
		"wdQcflg": "",
		"hm": "64",
		"hmQcflg": "",
		"pv": "2.4",
		"td": "-12.4",
		"pa": "1012.6",
		"paQcflg": "",
		"ps": "1023.7",
		"psQcflg": "",
		"ss": "",
		"ssQcflg": "9",
		"icsr": "",
		"dsnw": "",
		"hr3Fhsc": "",
		"dc10Tca": "0",
		"dc10LmcsCa": "0",
		"clfmAbbrCd": "",
		"lcsCh": "",
		"vs": "2000",
		"gndSttCd": "",
		"dmstMtphNo": "",
		"ts": "-6.2",
		"tsQcflg": "",
		"m005Te": "-0.6",
		"m01Te": "-0.8",
		"m02Te": "-0.4",
		"m03Te": "0.1"
	},
	{
		"tm": "2022-01-29 06:00",
		"rnum": "7",
		"stnId": "108",
		"stnNm": "서울",
		"ta": "-6.9",
		"taQcflg": "",
		"rn": "",
		"rnQcflg": "",
		"ws": "1.2",
		"wsQcflg": "",
		"wd": "270",
		"wdQcflg": "",
		"hm": "66",
		"hmQcflg": "",
		"pv": "2.4",
		"td": "-12.1",
		"pa": "1012.1",
		"paQcflg": "",
		"ps": "1023.2",
		"psQcflg": "",
		"ss": "",
		"ssQcflg": "9",
		"icsr": "",
		"dsnw": "",
		"hr3Fhsc": "",
		"dc10Tca": "0",
		"dc10LmcsCa": "0",
		"clfmAbbrCd": "",
		"lcsCh": "",
		"vs": "2000",
		"gndSttCd": "",
		"dmstMtphNo": "",
		"ts": "-6.6",
		"tsQcflg": "",
		"m005Te": "-0.7",
		"m01Te": "-0.8",
		"m02Te": "-0.4",
		"m03Te": "0.1"
	},
	{
		"tm": "2022-01-29 07:00",
		"rnum": "8",
		"stnId": "108",
		"stnNm": "서울",
		"ta": "-7.0",
		"taQcflg": "",
		"rn": "",
		"rnQcflg": "",
		"ws": "0.6",
		"wsQcflg": "",
		"wd": "290",
		"wdQcflg": "",
		"hm": "67",
		"hmQcflg": "",
		"pv": "2.4",
		"td": "-12.1",
		"pa": "1012.4",
		"paQcflg": "",
		"ps": "1023.6",
		"psQcflg": "",
		"ss": "",
		"ssQcflg": "9",
		"icsr": "",
		"dsnw": "",
		"hr3Fhsc": "",
		"dc10Tca": "0",
		"dc10LmcsCa": "0",
		"clfmAbbrCd": "",
		"lcsCh": "",
		"vs": "2000",
		"gndSttCd": "",
		"dmstMtphNo": "",
		"ts": "-6.9",
		"tsQcflg": "",
		"m005Te": "-0.8",
		"m01Te": "-0.9",
		"m02Te": "-0.4",
		"m03Te": "0.1"
	},
	{
		"tm": "2022-01-29 08:00",
		"rnum": "9",
		"stnId": "108",
		"stnNm": "서울",
		"ta": "-7.0",
		"taQcflg": "",
		"rn": "",
		"rnQcflg": "",
		"ws": "2.0",
		"wsQcflg": "",
		"wd": "320",
		"wdQcflg": "",
		"hm": "67",
		"hmQcflg": "",
		"pv": "2.4",
		"td": "-12.1",
		"pa": "1012.7",
		"paQcflg": "",
		"ps": "1023.9",
		"psQcflg": "",
		"ss": "0.1",
		"ssQcflg": "",
		"icsr": "0.01",
		"dsnw": "",
		"hr3Fhsc": "",
		"dc10Tca": "0",
		"dc10LmcsCa": "0",
		"clfmAbbrCd": "",
		"lcsCh": "",
		"vs": "2000",
		"gndSttCd": "",
		"dmstMtphNo": "",
		"ts": "-6.8",
		"tsQcflg": "",
		"m005Te": "-0.9",
		"m01Te": "-1.0",
		"m02Te": "-0.4",
		"m03Te": "0.1"
	},
	{
		"tm": "2022-01-29 09:00",
		"rnum": "10",
		"stnId": "108",
		"stnNm": "서울",
		"ta": "-6.1",
		"taQcflg": "",
		"rn": "",
		"rnQcflg": "",
		"ws": "2.7",
		"wsQcflg": "",
		"wd": "320",
		"wdQcflg": "",
		"hm": "58",
		"hmQcflg": "",
		"pv": "2.3",
		"td": "-13.0",
		"pa": "1012.8",
		"paQcflg": "",
		"ps": "1023.9",
		"psQcflg": "",
		"ss": "1.0",
		"ssQcflg": "",
		"icsr": "0.39",
		"dsnw": "",
		"hr3Fhsc": "",
		"dc10Tca": "1",
		"dc10LmcsCa": "0",
		"clfmAbbrCd": "Ci",
		"lcsCh": "",
		"vs": "2000",
		"gndSttCd": "",
		"dmstMtphNo": "",
		"ts": "-5.1",
		"tsQcflg": "",
		"m005Te": "-1.0",
		"m01Te": "-1.1",
		"m02Te": "-0.5",
		"m03Te": "0.1"
	},
	{
		"tm": "2022-01-29 10:00",
		"rnum": "11",
		"stnId": "108",
		"stnNm": "서울",
		"ta": "-4.5",
		"taQcflg": "",
		"rn": "",
		"rnQcflg": "",
		"ws": "2.9",
		"wsQcflg": "",
		"wd": "290",
		"wdQcflg": "",
		"hm": "49",
		"hmQcflg": "",
		"pv": "2.1",
		"td": "-13.6",
		"pa": "1013.0",
		"paQcflg": "",
		"ps": "1024.1",
		"psQcflg": "",
		"ss": "1.0",
		"ssQcflg": "",
		"icsr": "1.08",
		"dsnw": "",
		"hr3Fhsc": "",
		"dc10Tca": "2",
		"dc10LmcsCa": "0",
		"clfmAbbrCd": "Ci",
		"lcsCh": "",
		"vs": "2000",
		"gndSttCd": "",
		"dmstMtphNo": "",
		"ts": "-1.1",
		"tsQcflg": "",
		"m005Te": "-0.9",
		"m01Te": "-1.1",
		"m02Te": "-0.5",
		"m03Te": "0.1"
	},
	{
		"tm": "2022-01-29 11:00",
		"rnum": "12",
		"stnId": "108",
		"stnNm": "서울",
		"ta": "-3.6",
		"taQcflg": "",
		"rn": "",
		"rnQcflg": "",
		"ws": "2.9",
		"wsQcflg": "",
		"wd": "290",
		"wdQcflg": "",
		"hm": "45",
		"hmQcflg": "",
		"pv": "2.1",
		"td": "-13.8",
		"pa": "1012.6",
		"paQcflg": "",
		"ps": "1023.6",
		"psQcflg": "",
		"ss": "1.0",
		"ssQcflg": "",
		"icsr": "1.69",
		"dsnw": "",
		"hr3Fhsc": "",
		"dc10Tca": "2",
		"dc10LmcsCa": "0",
		"clfmAbbrCd": "Ci",
		"lcsCh": "",
		"vs": "2000",
		"gndSttCd": "",
		"dmstMtphNo": "",
		"ts": "1.8",
		"tsQcflg": "",
		"m005Te": "-0.7",
		"m01Te": "-1.0",
		"m02Te": "-0.5",
		"m03Te": "0.1"
	},
	{
		"tm": "2022-01-29 12:00",
		"rnum": "13",
		"stnId": "108",
		"stnNm": "서울",
		"ta": "-1.9",
		"taQcflg": "",
		"rn": "",
		"rnQcflg": "",
		"ws": "2.6",
		"wsQcflg": "",
		"wd": "290",
		"wdQcflg": "",
		"hm": "40",
		"hmQcflg": "",
		"pv": "2.1",
		"td": "-13.7",
		"pa": "1012.0",
		"paQcflg": "",
		"ps": "1022.9",
		"psQcflg": "",
		"ss": "1.0",
		"ssQcflg": "",
		"icsr": "2.08",
		"dsnw": "",
		"hr3Fhsc": "",
		"dc10Tca": "0",
		"dc10LmcsCa": "0",
		"clfmAbbrCd": "",
		"lcsCh": "",
		"vs": "2000",
		"gndSttCd": "",
		"dmstMtphNo": "",
		"ts": "6.6",
		"tsQcflg": "",
		"m005Te": "-0.5",
		"m01Te": "-0.9",
		"m02Te": "-0.5",
		"m03Te": "0.1"
	},
	{
		"tm": "2022-01-29 13:00",
		"rnum": "14",
		"stnId": "108",
		"stnNm": "서울",
		"ta": "-0.6",
		"taQcflg": "",
		"rn": "",
		"rnQcflg": "",
		"ws": "2.5",
		"wsQcflg": "",
		"wd": "290",
		"wdQcflg": "",
		"hm": "34",
		"hmQcflg": "",
		"pv": "2.0",
		"td": "-14.5",
		"pa": "1011.5",
		"paQcflg": "",
		"ps": "1022.4",
		"psQcflg": "",
		"ss": "1.0",
		"ssQcflg": "",
		"icsr": "2.26",
		"dsnw": "",
		"hr3Fhsc": "",
		"dc10Tca": "0",
		"dc10LmcsCa": "0",
		"clfmAbbrCd": "",
		"lcsCh": "",
		"vs": "2000",
		"gndSttCd": "",
		"dmstMtphNo": "",
		"ts": "9.4",
		"tsQcflg": "",
		"m005Te": "-0.3",
		"m01Te": "-0.8",
		"m02Te": "-0.5",
		"m03Te": "0.1"
	},
	{
		"tm": "2022-01-29 14:00",
		"rnum": "15",
		"stnId": "108",
		"stnNm": "서울",
		"ta": "-0.3",
		"taQcflg": "",
		"rn": "",
		"rnQcflg": "",
		"ws": "3.0",
		"wsQcflg": "",
		"wd": "290",
		"wdQcflg": "",
		"hm": "34",
		"hmQcflg": "",
		"pv": "2.0",
		"td": "-14.2",
		"pa": "1010.8",
		"paQcflg": "",
		"ps": "1021.6",
		"psQcflg": "",
		"ss": "1.0",
		"ssQcflg": "",
		"icsr": "2.22",
		"dsnw": "",
		"hr3Fhsc": "",
		"dc10Tca": "0",
		"dc10LmcsCa": "0",
		"clfmAbbrCd": "",
		"lcsCh": "",
		"vs": "2000",
		"gndSttCd": "",
		"dmstMtphNo": "",
		"ts": "9.3",
		"tsQcflg": "",
		"m005Te": "-0.2",
		"m01Te": "-0.7",
		"m02Te": "-0.5",
		"m03Te": "0.1"
	},
	{
		"tm": "2022-01-29 15:00",
		"rnum": "16",
		"stnId": "108",
		"stnNm": "서울",
		"ta": "0.1",
		"taQcflg": "",
		"rn": "",
		"rnQcflg": "",
		"ws": "4.3",
		"wsQcflg": "",
		"wd": "320",
		"wdQcflg": "",
		"hm": "29",
		"hmQcflg": "",
		"pv": "1.8",
		"td": "-15.8",
		"pa": "1009.8",
		"paQcflg": "",
		"ps": "1020.6",
		"psQcflg": "",
		"ss": "1.0",
		"ssQcflg": "",
		"icsr": "1.95",
		"dsnw": "",
		"hr3Fhsc": "",
		"dc10Tca": "0",
		"dc10LmcsCa": "0",
		"clfmAbbrCd": "",
		"lcsCh": "",
		"vs": "2000",
		"gndSttCd": "",
		"dmstMtphNo": "",
		"ts": "7.7",
		"tsQcflg": "",
		"m005Te": "-0.1",
		"m01Te": "-0.7",
		"m02Te": "-0.5",
		"m03Te": "0.1"
	},
	{
		"tm": "2022-01-29 16:00",
		"rnum": "17",
		"stnId": "108",
		"stnNm": "서울",
		"ta": "0.2",
		"taQcflg": "",
		"rn": "",
		"rnQcflg": "",
		"ws": "4.5",
		"wsQcflg": "",
		"wd": "290",
		"wdQcflg": "",
		"hm": "29",
		"hmQcflg": "",
		"pv": "1.8",
		"td": "-15.7",
		"pa": "1009.8",
		"paQcflg": "",
		"ps": "1020.6",
		"psQcflg": "",
		"ss": "1.0",
		"ssQcflg": "",
		"icsr": "1.47",
		"dsnw": "",
		"hr3Fhsc": "",
		"dc10Tca": "0",
		"dc10LmcsCa": "0",
		"clfmAbbrCd": "",
		"lcsCh": "",
		"vs": "2000",
		"gndSttCd": "",
		"dmstMtphNo": "",
		"ts": "2.1",
		"tsQcflg": "",
		"m005Te": "-0.1",
		"m01Te": "-0.6",
		"m02Te": "-0.5",
		"m03Te": "0.1"
	},
	{
		"tm": "2022-01-29 17:00",
		"rnum": "18",
		"stnId": "108",
		"stnNm": "서울",
		"ta": "0.5",
		"taQcflg": "",
		"rn": "",
		"rnQcflg": "",
		"ws": "2.6",
		"wsQcflg": "",
		"wd": "270",
		"wdQcflg": "",
		"hm": "29",
		"hmQcflg": "",
		"pv": "1.8",
		"td": "-15.5",
		"pa": "1009.6",
		"paQcflg": "",
		"ps": "1020.4",
		"psQcflg": "",
		"ss": "1.0",
		"ssQcflg": "",
		"icsr": "0.76",
		"dsnw": "",
		"hr3Fhsc": "",
		"dc10Tca": "0",
		"dc10LmcsCa": "0",
		"clfmAbbrCd": "",
		"lcsCh": "",
		"vs": "2000",
		"gndSttCd": "",
		"dmstMtphNo": "",
		"ts": "-0.2",
		"tsQcflg": "",
		"m005Te": "0.0",
		"m01Te": "-0.6",
		"m02Te": "-0.5",
		"m03Te": "0.1"
	},
	{
		"tm": "2022-01-29 18:00",
		"rnum": "19",
		"stnId": "108",
		"stnNm": "서울",
		"ta": "-0.9",
		"taQcflg": "",
		"rn": "",
		"rnQcflg": "",
		"ws": "2.7",
		"wsQcflg": "",
		"wd": "270",
		"wdQcflg": "",
		"hm": "32",
		"hmQcflg": "",
		"pv": "1.8",
		"td": "-15.5",
		"pa": "1010.0",
		"paQcflg": "",
		"ps": "1020.9",
		"psQcflg": "",
		"ss": "0.4",
		"ssQcflg": "",
		"icsr": "0.16",
		"dsnw": "",
		"hr3Fhsc": "",
		"dc10Tca": "0",
		"dc10LmcsCa": "0",
		"clfmAbbrCd": "",
		"lcsCh": "",
		"vs": "2000",
		"gndSttCd": "",
		"dmstMtphNo": "",
		"ts": "-1.1",
		"tsQcflg": "",
		"m005Te": "0.0",
		"m01Te": "-0.5",
		"m02Te": "-0.5",
		"m03Te": "0.1"
	},
	{
		"tm": "2022-01-29 19:00",
		"rnum": "20",
		"stnId": "108",
		"stnNm": "서울",
		"ta": "-1.6",
		"taQcflg": "",
		"rn": "",
		"rnQcflg": "",
		"ws": "2.6",
		"wsQcflg": "",
		"wd": "200",
		"wdQcflg": "",
		"hm": "42",
		"hmQcflg": "",
		"pv": "2.3",
		"td": "-12.8",
		"pa": "1010.2",
		"paQcflg": "",
		"ps": "1021.1",
		"psQcflg": "",
		"ss": "",
		"ssQcflg": "9",
		"icsr": "",
		"dsnw": "",
		"hr3Fhsc": "",
		"dc10Tca": "0",
		"dc10LmcsCa": "0",
		"clfmAbbrCd": "",
		"lcsCh": "",
		"vs": "2000",
		"gndSttCd": "",
		"dmstMtphNo": "",
		"ts": "-1.9",
		"tsQcflg": "",
		"m005Te": "0.0",
		"m01Te": "-0.5",
		"m02Te": "-0.5",
		"m03Te": "0.1"
	},
	{
		"tm": "2022-01-29 20:00",
		"rnum": "21",
		"stnId": "108",
		"stnNm": "서울",
		"ta": "-2.3",
		"taQcflg": "",
		"rn": "",
		"rnQcflg": "",
		"ws": "0.8",
		"wsQcflg": "",
		"wd": "200",
		"wdQcflg": "",
		"hm": "52",
		"hmQcflg": "",
		"pv": "2.7",
		"td": "-10.8",
		"pa": "1010.6",
		"paQcflg": "",
		"ps": "1021.5",
		"psQcflg": "",
		"ss": "",
		"ssQcflg": "9",
		"icsr": "",
		"dsnw": "",
		"hr3Fhsc": "",
		"dc10Tca": "0",
		"dc10LmcsCa": "0",
		"clfmAbbrCd": "",
		"lcsCh": "",
		"vs": "2000",
		"gndSttCd": "",
		"dmstMtphNo": "",
		"ts": "-2.5",
		"tsQcflg": "",
		"m005Te": "-0.1",
		"m01Te": "-0.5",
		"m02Te": "-0.5",
		"m03Te": "0.2"
	},
	{
		"tm": "2022-01-29 21:00",
		"rnum": "22",
		"stnId": "108",
		"stnNm": "서울",
		"ta": "-2.7",
		"taQcflg": "",
		"rn": "",
		"rnQcflg": "",
		"ws": "1.2",
		"wsQcflg": "",
		"wd": "340",
		"wdQcflg": "",
		"hm": "54",
		"hmQcflg": "",
		"pv": "2.7",
		"td": "-10.7",
		"pa": "1010.4",
		"paQcflg": "",
		"ps": "1021.4",
		"psQcflg": "",
		"ss": "",
		"ssQcflg": "9",
		"icsr": "",
		"dsnw": "",
		"hr3Fhsc": "",
		"dc10Tca": "0",
		"dc10LmcsCa": "0",
		"clfmAbbrCd": "",
		"lcsCh": "",
		"vs": "2000",
		"gndSttCd": "",
		"dmstMtphNo": "",
		"ts": "-3.3",
		"tsQcflg": "",
		"m005Te": "-0.1",
		"m01Te": "-0.6",
		"m02Te": "-0.4",
		"m03Te": "0.1"
	},
	{
		"tm": "2022-01-29 22:00",
		"rnum": "23",
		"stnId": "108",
		"stnNm": "서울",
		"ta": "-3.4",
		"taQcflg": "",
		"rn": "",
		"rnQcflg": "",
		"ws": "1.5",
		"wsQcflg": "",
		"wd": "320",
		"wdQcflg": "",
		"hm": "43",
		"hmQcflg": "",
		"pv": "2.0",
		"td": "-14.2",
		"pa": "1010.8",
		"paQcflg": "",
		"ps": "1021.8",
		"psQcflg": "",
		"ss": "",
		"ssQcflg": "9",
		"icsr": "",
		"dsnw": "",
		"hr3Fhsc": "",
		"dc10Tca": "0",
		"dc10LmcsCa": "0",
		"clfmAbbrCd": "",
		"lcsCh": "",
		"vs": "2000",
		"gndSttCd": "",
		"dmstMtphNo": "",
		"ts": "-3.9",
		"tsQcflg": "",
		"m005Te": "-0.2",
		"m01Te": "-0.6",
		"m02Te": "-0.4",
		"m03Te": "0.2"
	},
	{
		"tm": "2022-01-29 23:00",
		"rnum": "24",
		"stnId": "108",
		"stnNm": "서울",
		"ta": "-4.1",
		"taQcflg": "",
		"rn": "",
		"rnQcflg": "",
		"ws": "1.7",
		"wsQcflg": "",
		"wd": "270",
		"wdQcflg": "",
		"hm": "47",
		"hmQcflg": "",
		"pv": "2.1",
		"td": "-13.7",
		"pa": "1011.1",
		"paQcflg": "",
		"ps": "1022.1",
		"psQcflg": "",
		"ss": "",
		"ssQcflg": "9",
		"icsr": "",
		"dsnw": "",
		"hr3Fhsc": "",
		"dc10Tca": "0",
		"dc10LmcsCa": "0",
		"clfmAbbrCd": "",
		"lcsCh": "",
		"vs": "2000",
		"gndSttCd": "",
		"dmstMtphNo": "",
		"ts": "-4.4",
		"tsQcflg": "",
		"m005Te": "-0.3",
		"m01Te": "-0.7",
		"m02Te": "-0.4",
		"m03Te": "0.1"
	}
]