[
	{
		"tm": "2022-01-18 00:00",
		"rnum": "1",
		"stnId": "108",
		"stnNm": "서울",
		"ta": "-7.7",
		"taQcflg": "",
		"rn": "",
		"rnQcflg": "9",
		"ws": "2.2",
		"wsQcflg": "",
		"wd": "270",
		"wdQcflg": "",
		"hm": "56",
		"hmQcflg": "",
		"pv": "1.9",
		"td": "-14.9",
		"pa": "1017.9",
		"paQcflg": "",
		"ps": "1029.1",
		"psQcflg": "",
		"ss": "",
		"ssQcflg": "9",
		"icsr": "",
		"dsnw": "0.5",
		"hr3Fhsc": "",
		"dc10Tca": "0",
		"dc10LmcsCa": "0",
		"clfmAbbrCd": "",
		"lcsCh": "",
		"vs": "2000",
		"gndSttCd": "",
		"dmstMtphNo": "",
		"ts": "-5.9",
		"tsQcflg": "",
		"m005Te": "-0.9",
		"m01Te": "-1.1",
		"m02Te": "-0.7",
		"m03Te": "0.0"
	},
	{
		"tm": "2022-01-18 01:00",
		"rnum": "2",
		"stnId": "108",
		"stnNm": "서울",
		"ta": "-7.6",
		"taQcflg": "",
		"rn": "",
		"rnQcflg": "",
		"ws": "2.3",
		"wsQcflg": "",
		"wd": "340",
		"wdQcflg": "",
		"hm": "56",
		"hmQcflg": "",
		"pv": "1.9",
		"td": "-14.8",
		"pa": "1017.8",
		"paQcflg": "",
		"ps": "1029.0",
		"psQcflg": "",
		"ss": "",
		"ssQcflg": "9",
		"icsr": "",
		"dsnw": "0.5",
		"hr3Fhsc": "",
		"dc10Tca": "0",
		"dc10LmcsCa": "0",
		"clfmAbbrCd": "",
		"lcsCh": "",
		"vs": "2000",
		"gndSttCd": "",
		"dmstMtphNo": "",
		"ts": "-6.2",
		"tsQcflg": "",
		"m005Te": "-1.0",
		"m01Te": "-1.2",
		"m02Te": "-0.8",
		"m03Te": "0.0"
	},
	{
		"tm": "2022-01-18 02:00",
		"rnum": "3",
		"stnId": "108",
		"stnNm": "서울",
		"ta": "-7.9",
		"taQcflg": "",
		"rn": "",
		"rnQcflg": "",
		"ws": "2.0",
		"wsQcflg": "",
		"wd": "340",
		"wdQcflg": "",
		"hm": "56",
		"hmQcflg": "",
		"pv": "1.9",
		"td": "-15.1",
		"pa": "1017.8",
		"paQcflg": "",
		"ps": "1029.1",
		"psQcflg": "",
		"ss": "",
		"ssQcflg": "9",
		"icsr": "",
		"dsnw": "0.5",
		"hr3Fhsc": "",
		"dc10Tca": "0",
		"dc10LmcsCa": "0",
		"clfmAbbrCd": "",
		"lcsCh": "",
		"vs": "2000",
		"gndSttCd": "",
		"dmstMtphNo": "",
		"ts": "-6.5",
		"tsQcflg": "",
		"m005Te": "-1.1",
		"m01Te": "-1.3",
		"m02Te": "-0.8",
		"m03Te": "0.0"
	},
	{
		"tm": "2022-01-18 03:00",
		"rnum": "4",
		"stnId": "108",
		"stnNm": "서울",
		"ta": "-8.4",
		"taQcflg": "",
		"rn": "",
		"rnQcflg": "",
		"ws": "1.7",
		"wsQcflg": "",
		"wd": "290",
		"wdQcflg": "",
		"hm": "58",
		"hmQcflg": "",
		"pv": "1.9",
		"td": "-15.2",
		"pa": "1018.1",
		"paQcflg": "",
		"ps": "1029.4",
		"psQcflg": "",
		"ss": "",
		"ssQcflg": "9",
		"icsr": "",
		"dsnw": "0.5",
		"hr3Fhsc": "",
		"dc10Tca": "0",
		"dc10LmcsCa": "0",
		"clfmAbbrCd": "",
		"lcsCh": "",
		"vs": "2000",
		"gndSttCd": "",
		"dmstMtphNo": "",
		"ts": "-6.9",
		"tsQcflg": "",
		"m005Te": "-1.3",
		"m01Te": "-1.4",
		"m02Te": "-0.9",
		"m03Te": "0.0"
	},
	{
		"tm": "2022-01-18 04:00",
		"rnum": "5",
		"stnId": "108",
		"stnNm": "서울",
		"ta": "-8.9",
		"taQcflg": "",
		"rn": "",
		"rnQcflg": "",
		"ws": "1.3",
		"wsQcflg": "",
		"wd": "270",
		"wdQcflg": "",
		"hm": "58",
		"hmQcflg": "",
		"pv": "1.8",
		"td": "-15.6",
		"pa": "1018.0",
		"paQcflg": "",
		"ps": "1029.3",
		"psQcflg": "",
		"ss": "",
		"ssQcflg": "9",
		"icsr": "",
		"dsnw": "0.5",
		"hr3Fhsc": "",
		"dc10Tca": "0",
		"dc10LmcsCa": "0",
		"clfmAbbrCd": "",
		"lcsCh": "",
		"vs": "2000",
		"gndSttCd": "",
		"dmstMtphNo": "",
		"ts": "-7.3",
		"tsQcflg": "",
		"m005Te": "-1.4",
		"m01Te": "-1.5",
		"m02Te": "-0.9",
		"m03Te": "0.0"
	},
	{
		"tm": "2022-01-18 05:00",
		"rnum": "6",
		"stnId": "108",
		"stnNm": "서울",
		"ta": "-9.1",
		"taQcflg": "",
		"rn": "",
		"rnQcflg": "",
		"ws": "1.5",
		"wsQcflg": "",
		"wd": "290",
		"wdQcflg": "",
		"hm": "60",
		"hmQcflg": "",
		"pv": "1.8",
		"td": "-15.4",
		"pa": "1018.0",
		"paQcflg": "",
		"ps": "1029.3",
		"psQcflg": "",
		"ss": "",
		"ssQcflg": "9",
		"icsr": "",
		"dsnw": "0.5",
		"hr3Fhsc": "",
		"dc10Tca": "0",
		"dc10LmcsCa": "0",
		"clfmAbbrCd": "",
		"lcsCh": "",
		"vs": "2000",
		"gndSttCd": "",
		"dmstMtphNo": "",
		"ts": "-7.5",
		"tsQcflg": "",
		"m005Te": "-1.5",
		"m01Te": "-1.6",
		"m02Te": "-1.0",
		"m03Te": "0.0"
	},
	{
		"tm": "2022-01-18 06:00",
		"rnum": "7",
		"stnId": "108",
		"stnNm": "서울",
		"ta": "-9.6",
		"taQcflg": "",
		"rn": "",
		"rnQcflg": "",
		"ws": "1.9",
		"wsQcflg": "",
		"wd": "270",
		"wdQcflg": "",
		"hm": "62",
		"hmQcflg": "",
		"pv": "1.8",
		"td": "-15.5",
		"pa": "1018.1",
		"paQcflg": "",
		"ps": "1029.4",
		"psQcflg": "",
		"ss": "",
		"ssQcflg": "9",
		"icsr": "",
		"dsnw": "0.5",
		"hr3Fhsc": "",
		"dc10Tca": "0",
		"dc10LmcsCa": "0",
		"clfmAbbrCd": "",
		"lcsCh": "",
		"vs": "2000",
		"gndSttCd": "",
		"dmstMtphNo": "",
		"ts": "-7.7",
		"tsQcflg": "",
		"m005Te": "-1.6",
		"m01Te": "-1.7",
		"m02Te": "-1.0",
		"m03Te": "0.0"
	},
	{
		"tm": "2022-01-18 07:00",
		"rnum": "8",
		"stnId": "108",
		"stnNm": "서울",
		"ta": "-9.4",
		"taQcflg": "",
		"rn": "",
		"rnQcflg": "",
		"ws": "2.1",
		"wsQcflg": "",
		"wd": "270",
		"wdQcflg": "",
		"hm": "59",
		"hmQcflg": "",
		"pv": "1.8",
		"td": "-15.9",
		"pa": "1018.5",
		"paQcflg": "",
		"ps": "1029.8",
		"psQcflg": "",
		"ss": "",
		"ssQcflg": "9",
		"icsr": "",
		"dsnw": "0.5",
		"hr3Fhsc": "",
		"dc10Tca": "0",
		"dc10LmcsCa": "0",
		"clfmAbbrCd": "",
		"lcsCh": "",
		"vs": "2000",
		"gndSttCd": "",
		"dmstMtphNo": "",
		"ts": "-7.6",
		"tsQcflg": "",
		"m005Te": "-1.8",
		"m01Te": "-1.8",
		"m02Te": "-1.1",
		"m03Te": "0.0"
	},
	{
		"tm": "2022-01-18 08:00",
		"rnum": "9",
		"stnId": "108",
		"stnNm": "서울",
		"ta": "-9.6",
		"taQcflg": "",
		"rn": "",
		"rnQcflg": "",
		"ws": "2.4",
		"wsQcflg": "",
		"wd": "340",
		"wdQcflg": "",
		"hm": "61",
		"hmQcflg": "",
		"pv": "1.8",
		"td": "-15.7",
		"pa": "1018.7",
		"paQcflg": "",
		"ps": "1030.0",
		"psQcflg": "",
		"ss": "0.0",
		"ssQcflg": "",
		"icsr": "0.0",
		"dsnw": "0.4",
		"hr3Fhsc": "",
		"dc10Tca": "0",
		"dc10LmcsCa": "0",
		"clfmAbbrCd": "",
		"lcsCh": "",
		"vs": "2000",
		"gndSttCd": "",
		"dmstMtphNo": "",
		"ts": "-7.7",
		"tsQcflg": "",
		"m005Te": "-1.8",
		"m01Te": "-1.9",
		"m02Te": "-1.2",
		"m03Te": "0.0"
	},
	{
		"tm": "2022-01-18 09:00",
		"rnum": "10",
		"stnId": "108",
		"stnNm": "서울",
		"ta": "-8.8",
		"taQcflg": "",
		"rn": "",
		"rnQcflg": "",
		"ws": "3.2",
		"wsQcflg": "",
		"wd": "320",
		"wdQcflg": "",
		"hm": "56",
		"hmQcflg": "",
		"pv": "1.8",
		"td": "-16.0",
		"pa": "1019.2",
		"paQcflg": "",
		"ps": "1030.5",
		"psQcflg": "",
		"ss": "0.9",
		"ssQcflg": "",
		"icsr": "0.34",
		"dsnw": "0.4",
		"hr3Fhsc": "",
		"dc10Tca": "0",
		"dc10LmcsCa": "0",
		"clfmAbbrCd": "",
		"lcsCh": "",
		"vs": "2000",
		"gndSttCd": "",
		"dmstMtphNo": "",
		"ts": "-6.7",
		"tsQcflg": "",
		"m005Te": "-1.9",
		"m01Te": "-2.0",
		"m02Te": "-1.2",
		"m03Te": "-0.1"
	},
	{
		"tm": "2022-01-18 10:00",
		"rnum": "11",
		"stnId": "108",
		"stnNm": "서울",
		"ta": "-7.5",
		"taQcflg": "",
		"rn": "",
		"rnQcflg": "",
		"ws": "3.0",
		"wsQcflg": "",
		"wd": "290",
		"wdQcflg": "",
		"hm": "51",
		"hmQcflg": "",
		"pv": "1.8",
		"td": "-15.9",
		"pa": "1019.4",
		"paQcflg": "",
		"ps": "1030.7",
		"psQcflg": "",
		"ss": "1.0",
		"ssQcflg": "",
		"icsr": "0.95",
		"dsnw": "0.4",
		"hr3Fhsc": "",
		"dc10Tca": "0",
		"dc10LmcsCa": "0",
		"clfmAbbrCd": "",
		"lcsCh": "",
		"vs": "2000",
		"gndSttCd": "",
		"dmstMtphNo": "",
		"ts": "-2.9",
		"tsQcflg": "",
		"m005Te": "-1.8",
		"m01Te": "-2.0",
		"m02Te": "-1.3",
		"m03Te": "-0.1"
	},
	{
		"tm": "2022-01-18 11:00",
		"rnum": "12",
		"stnId": "108",
		"stnNm": "서울",
		"ta": "-5.6",
		"taQcflg": "",
		"rn": "",
		"rnQcflg": "",
		"ws": "2.9",
		"wsQcflg": "",
		"wd": "270",
		"wdQcflg": "",
		"hm": "44",
		"hmQcflg": "",
		"pv": "1.8",
		"td": "-15.9",
		"pa": "1019.3",
		"paQcflg": "",
		"ps": "1030.5",
		"psQcflg": "",
		"ss": "1.0",
		"ssQcflg": "",
		"icsr": "1.56",
		"dsnw": "0.3",
		"hr3Fhsc": "",
		"dc10Tca": "0",
		"dc10LmcsCa": "0",
		"clfmAbbrCd": "",
		"lcsCh": "",
		"vs": "2000",
		"gndSttCd": "",
		"dmstMtphNo": "",
		"ts": "1.7",
		"tsQcflg": "",
		"m005Te": "-1.6",
		"m01Te": "-1.9",
		"m02Te": "-1.3",
		"m03Te": "-0.1"
	},
	{
		"tm": "2022-01-18 12:00",
		"rnum": "13",
		"stnId": "108",
		"stnNm": "서울",
		"ta": "-3.7",
		"taQcflg": "",
		"rn": "",
		"rnQcflg": "",
		"ws": "2.4",
		"wsQcflg": "",
		"wd": "250",
		"wdQcflg": "",
		"hm": "37",
		"hmQcflg": "",
		"pv": "1.7",
		"td": "-16.3",
		"pa": "1018.6",
		"paQcflg": "",
		"ps": "1029.7",
		"psQcflg": "",
		"ss": "1.0",
		"ssQcflg": "",
		"icsr": "1.93",
		"dsnw": "",
		"hr3Fhsc": "",
		"dc10Tca": "0",
		"dc10LmcsCa": "0",
		"clfmAbbrCd": "",
		"lcsCh": "",
		"vs": "2000",
		"gndSttCd": "",
		"dmstMtphNo": "",
		"ts": "6.4",
		"tsQcflg": "",
		"m005Te": "-1.3",
		"m01Te": "-1.7",
		"m02Te": "-1.3",
		"m03Te": "-0.1"
	},
	{
		"tm": "2022-01-18 13:00",
		"rnum": "14",
		"stnId": "108",
		"stnNm": "서울",
		"ta": "-3.0",
		"taQcflg": "",
		"rn": "",
		"rnQcflg": "",
		"ws": "2.8",
		"wsQcflg": "",
		"wd": "290",
		"wdQcflg": "",
		"hm": "32",
		"hmQcflg": "",
		"pv": "1.6",
		"td": "-17.4",
		"pa": "1017.6",
		"paQcflg": "",
		"ps": "1028.6",
		"psQcflg": "",
		"ss": "1.0",
		"ssQcflg": "",
		"icsr": "2.1",
		"dsnw": "",
		"hr3Fhsc": "",
		"dc10Tca": "0",
		"dc10LmcsCa": "0",
		"clfmAbbrCd": "",
		"lcsCh": "",
		"vs": "2000",
		"gndSttCd": "",
		"dmstMtphNo": "",
		"ts": "9.0",
		"tsQcflg": "",
		"m005Te": "-1.0",
		"m01Te": "-1.5",
		"m02Te": "-1.2",
		"m03Te": "-0.1"
	},
	{
		"tm": "2022-01-18 14:00",
		"rnum": "15",
		"stnId": "108",
		"stnNm": "서울",
		"ta": "-1.8",
		"taQcflg": "",
		"rn": "",
		"rnQcflg": "",
		"ws": "3.2",
		"wsQcflg": "",
		"wd": "270",
		"wdQcflg": "",
		"hm": "29",
		"hmQcflg": "",
		"pv": "1.6",
		"td": "-17.5",
		"pa": "1016.8",
		"paQcflg": "",
		"ps": "1027.8",
		"psQcflg": "",
		"ss": "1.0",
		"ssQcflg": "",
		"icsr": "2.04",
		"dsnw": "",
		"hr3Fhsc": "",
		"dc10Tca": "0",
		"dc10LmcsCa": "0",
		"clfmAbbrCd": "",
		"lcsCh": "",
		"vs": "2000",
		"gndSttCd": "",
		"dmstMtphNo": "",
		"ts": "8.9",
		"tsQcflg": "",
		"m005Te": "-0.8",
		"m01Te": "-1.4",
		"m02Te": "-1.1",
		"m03Te": "-0.1"
	},
	{
		"tm": "2022-01-18 15:00",
		"rnum": "16",
		"stnId": "108",
		"stnNm": "서울",
		"ta": "-1.0",
		"taQcflg": "",
		"rn": "",
		"rnQcflg": "",
		"ws": "3.1",
		"wsQcflg": "",
		"wd": "290",
		"wdQcflg": "",
		"hm": "29",
		"hmQcflg": "",
		"pv": "1.6",
		"td": "-16.8",
		"pa": "1016.1",
		"paQcflg": "",
		"ps": "1027.0",
		"psQcflg": "",
		"ss": "1.0",
		"ssQcflg": "",
		"icsr": "1.7",
		"dsnw": "",
		"hr3Fhsc": "",
		"dc10Tca": "0",
		"dc10LmcsCa": "0",
		"clfmAbbrCd": "",
		"lcsCh": "",
		"vs": "2000",
		"gndSttCd": "",
		"dmstMtphNo": "",
		"ts": "7.0",
		"tsQcflg": "",
		"m005Te": "-0.6",
		"m01Te": "-1.2",
		"m02Te": "-1.1",
		"m03Te": "-0.1"
	},
	{
		"tm": "2022-01-18 16:00",
		"rnum": "17",
		"stnId": "108",
		"stnNm": "서울",
		"ta": "-0.9",
		"taQcflg": "",
		"rn": "",
		"rnQcflg": "",
		"ws": "2.7",
		"wsQcflg": "",
		"wd": "270",
		"wdQcflg": "",
		"hm": "28",
		"hmQcflg": "",
		"pv": "1.6",
		"td": "-17.1",
		"pa": "1016.0",
		"paQcflg": "",
		"ps": "1026.9",
		"psQcflg": "",
		"ss": "1.0",
		"ssQcflg": "",
		"icsr": "1.18",
		"dsnw": "",
		"hr3Fhsc": "",
		"dc10Tca": "0",
		"dc10LmcsCa": "0",
		"clfmAbbrCd": "",
		"lcsCh": "",
		"vs": "2000",
		"gndSttCd": "",
		"dmstMtphNo": "",
		"ts": "0.3",
		"tsQcflg": "",
		"m005Te": "-0.5",
		"m01Te": "-1.1",
		"m02Te": "-1.0",
		"m03Te": "-0.1"
	},
	{
		"tm": "2022-01-18 17:00",
		"rnum": "18",
		"stnId": "108",
		"stnNm": "서울",
		"ta": "-1.9",
		"taQcflg": "",
		"rn": "",
		"rnQcflg": "",
		"ws": "2.8",
		"wsQcflg": "",
		"wd": "290",
		"wdQcflg": "",
		"hm": "32",
		"hmQcflg": "",
		"pv": "1.7",
		"td": "-16.4",
		"pa": "1016.3",
		"paQcflg": "",
		"ps": "1027.3",
		"psQcflg": "",
		"ss": "1.0",
		"ssQcflg": "",
		"icsr": "0.52",
		"dsnw": "",
		"hr3Fhsc": "",
		"dc10Tca": "0",
		"dc10LmcsCa": "0",
		"clfmAbbrCd": "",
		"lcsCh": "",
		"vs": "2000",
		"gndSttCd": "",
		"dmstMtphNo": "",
		"ts": "-1.3",
		"tsQcflg": "",
		"m005Te": "-0.5",
		"m01Te": "-1.0",
		"m02Te": "-0.9",
		"m03Te": "-0.1"
	},
	{
		"tm": "2022-01-18 18:00",
		"rnum": "19",
		"stnId": "108",
		"stnNm": "서울",
		"ta": "-3.0",
		"taQcflg": "",
		"rn": "",
		"rnQcflg": "",
		"ws": "1.6",
		"wsQcflg": "",
		"wd": "270",
		"wdQcflg": "",
		"hm": "33",
		"hmQcflg": "",
		"pv": "1.6",
		"td": "-17.0",
		"pa": "1016.3",
		"paQcflg": "",
		"ps": "1027.3",
		"psQcflg": "",
		"ss": "0.3",
		"ssQcflg": "",
		"icsr": "0.08",
		"dsnw": "",
		"hr3Fhsc": "",
		"dc10Tca": "0",
		"dc10LmcsCa": "0",
		"clfmAbbrCd": "",
		"lcsCh": "",
		"vs": "2000",
		"gndSttCd": "",
		"dmstMtphNo": "",
		"ts": "-2.8",
		"tsQcflg": "",
		"m005Te": "-0.5",
		"m01Te": "-1.0",
		"m02Te": "-0.9",
		"m03Te": "-0.1"
	},
	{
		"tm": "2022-01-18 19:00",
		"rnum": "20",
		"stnId": "108",
		"stnNm": "서울",
		"ta": "-3.6",
		"taQcflg": "",
		"rn": "",
		"rnQcflg": "",
		"ws": "2.8",
		"wsQcflg": "",
		"wd": "270",
		"wdQcflg": "",
		"hm": "38",
		"hmQcflg": "",
		"pv": "1.8",
		"td": "-15.8",
		"pa": "1016.7",
		"paQcflg": "",
		"ps": "1027.8",
		"psQcflg": "",
		"ss": "",
		"ssQcflg": "9",
		"icsr": "",
		"dsnw": "",
		"hr3Fhsc": "",
		"dc10Tca": "0",
		"dc10LmcsCa": "0",
		"clfmAbbrCd": "",
		"lcsCh": "",
		"vs": "2000",
		"gndSttCd": "",
		"dmstMtphNo": "",
		"ts": "-3.5",
		"tsQcflg": "",
		"m005Te": "-0.6",
		"m01Te": "-1.0",
		"m02Te": "-0.8",
		"m03Te": "-0.1"
	},
	{
		"tm": "2022-01-18 20:00",
		"rnum": "21",
		"stnId": "108",
		"stnNm": "서울",
		"ta": "-4.0",
		"taQcflg": "",
		"rn": "",
		"rnQcflg": "",
		"ws": "3.0",
		"wsQcflg": "",
		"wd": "290",
		"wdQcflg": "",
		"hm": "49",
		"hmQcflg": "",
		"pv": "2.2",
		"td": "-13.1",
		"pa": "1017.0",
		"paQcflg": "",
		"ps": "1028.1",
		"psQcflg": "",
		"ss": "",
		"ssQcflg": "9",
		"icsr": "",
		"dsnw": "",
		"hr3Fhsc": "",
		"dc10Tca": "4",
		"dc10LmcsCa": "0",
		"clfmAbbrCd": "",
		"lcsCh": "",
		"vs": "2000",
		"gndSttCd": "",
		"dmstMtphNo": "",
		"ts": "-4.1",
		"tsQcflg": "",
		"m005Te": "-0.7",
		"m01Te": "-1.1",
		"m02Te": "-0.8",
		"m03Te": "-0.1"
	},
	{
		"tm": "2022-01-18 21:00",
		"rnum": "22",
		"stnId": "108",
		"stnNm": "서울",
		"ta": "-4.7",
		"taQcflg": "",
		"rn": "",
		"rnQcflg": "",
		"ws": "2.3",
		"wsQcflg": "",
		"wd": "270",
		"wdQcflg": "",
		"hm": "52",
		"hmQcflg": "",
		"pv": "2.3",
		"td": "-13.0",
		"pa": "1017.5",
		"paQcflg": "",
		"ps": "1028.6",
		"psQcflg": "",
		"ss": "",
		"ssQcflg": "9",
		"icsr": "",
		"dsnw": "",
		"hr3Fhsc": "",
		"dc10Tca": "2",
		"dc10LmcsCa": "0",
		"clfmAbbrCd": "Ci",
		"lcsCh": "",
		"vs": "2000",
		"gndSttCd": "",
		"dmstMtphNo": "",
		"ts": "-4.6",
		"tsQcflg": "",
		"m005Te": "-0.8",
		"m01Te": "-1.1",
		"m02Te": "-0.8",
		"m03Te": "-0.1"
	},
	{
		"tm": "2022-01-18 22:00",
		"rnum": "23",
		"stnId": "108",
		"stnNm": "서울",
		"ta": "-5.2",
		"taQcflg": "",
		"rn": "",
		"rnQcflg": "",
		"ws": "1.4",
		"wsQcflg": "",
		"wd": "290",
		"wdQcflg": "",
		"hm": "55",
		"hmQcflg": "",
		"pv": "2.3",
		"td": "-12.8",
		"pa": "1017.0",
		"paQcflg": "",
		"ps": "1028.1",
		"psQcflg": "",
		"ss": "",
		"ssQcflg": "9",
		"icsr": "",
		"dsnw": "",
		"hr3Fhsc": "",
		"dc10Tca": "5",
		"dc10LmcsCa": "0",
		"clfmAbbrCd": "",
		"lcsCh": "",
		"vs": "2000",
		"gndSttCd": "",
		"dmstMtphNo": "",
		"ts": "-5.4",
		"tsQcflg": "",
		"m005Te": "-0.9",
		"m01Te": "-1.2",
		"m02Te": "-0.8",
		"m03Te": "-0.1"
	},
	{
		"tm": "2022-01-18 23:00",
		"rnum": "24",
		"stnId": "108",
		"stnNm": "서울",
		"ta": "-5.5",
		"taQcflg": "",
		"rn": "",
		"rnQcflg": "",
		"ws": "1.6",
		"wsQcflg": "",
		"wd": "290",
		"wdQcflg": "",
		"hm": "57",
		"hmQcflg": "",
		"pv": "2.3",
		"td": "-12.6",
		"pa": "1017.0",
		"paQcflg": "",
		"ps": "1028.1",
		"psQcflg": "",
		"ss": "",
		"ssQcflg": "9",
		"icsr": "",
		"dsnw": "",
		"hr3Fhsc": "",
		"dc10Tca": "2",
		"dc10LmcsCa": "0",
		"clfmAbbrCd": "",
		"lcsCh": "",
		"vs": "2000",
		"gndSttCd": "",
		"dmstMtphNo": "",
		"ts": "-5.9",
		"tsQcflg": "",
		"m005Te": "-1.1",
		"m01Te": "-1.3",
		"m02Te": "-0.9",
		"m03Te": "-0.1"
	}
]